pacifica_configparser-2.0.0-py3.6-nspkg.pth
pacifica/configparser/__init__.py
pacifica_configparser-2.0.0.dist-info/METADATA
pacifica_configparser-2.0.0.dist-info/RECORD
pacifica_configparser-2.0.0.dist-info/WHEEL
pacifica_configparser-2.0.0.dist-info/namespace_packages.txt
pacifica_configparser-2.0.0.dist-info/top_level.txt
