Metadata-Version: 2.1
Name: pacifica-configparser
Version: 2.0.0
Summary: Pacifica Configuration Parser
Home-page: UNKNOWN
Author: David Brown
Author-email: david.brown@pnnl.gov
License: UNKNOWN
Platform: UNKNOWN
Requires-Dist: setuptools
Requires-Dist: six
